dbmarkers/__init__.py
dbmarkers/_version.py
dbmarkers/common/__init__.py
dbmarkers/common/madmom.py
dbmarkers/common/parser.py
dbmarkers/common/validators.py
dbmarkers/reaper/__init__.py
dbmarkers/reaper/main.py
dbmarkers/templates/__init__.py
dbmarkers/templates/reaper.j2
dbmarkers/templates/transcribe.j2
dbmarkers/transcribe/__init__.py
dbmarkers/transcribe/main.py
dbmarkers-0.1.0.dist-info/LICENSE
dbmarkers-0.1.0.dist-info/METADATA
dbmarkers-0.1.0.dist-info/WHEEL
dbmarkers-0.1.0.dist-info/entry_points.txt
dbmarkers-0.1.0.dist-info/top_level.txt
dbmarkers-0.1.0.dist-info/RECORD
