Metadata-Version: 2.2
Name: dbmarkers
Version: 0.1.0
Summary: Generates Downbeat markers for DAWs and other musical apps
Author-email: Rafael González <astrorafael@gmail.com>
License: MIT License
Project-URL: Homepage, https://github.com/astrorafael/dbmarkers
Project-URL: Repository, https://github.com/astrorafael/dbmarkers.git
Classifier: Operating System :: POSIX :: Linux
Classifier: Programming Language :: Python :: 3.10
Classifier: Programming Language :: Python :: 3.11
Classifier: Programming Language :: Python :: 3.12
Classifier: Development Status :: 4 - Beta
Classifier: Environment :: Console
Classifier: Intended Audience :: End Users/Desktop
Classifier: License :: OSI Approved :: MIT License
Requires-Python: >=3.10
License-File: LICENSE
Requires-Dist: lica>=1.1
Requires-Dist: jinja2
